{"nodes": [{"id": "checkout_actions", "label": "submitCheckout Server Action", "file_type": "code", "source_file": "D:\\BD shopify\\apps\\web\\app\\%5Fsites\\[tenant]\\checkout\\actions.ts", "source_location": null, "source_url": null, "captured_at": null, "author": null, "contributor": null}, {"id": "lib_place_order", "label": "placeOrder idempotent txn", "file_type": "code", "source_file": "D:\\BD shopify\\apps\\web\\app\\%5Fsites\\[tenant]\\checkout\\actions.ts", "source_location": null, "source_url": null, "captured_at": null, "author": null, "contributor": null}, {"id": "db_withTenant", "label": "withTenant / asPlatformAdmin (@hybrid/db)", "file_type": "code", "source_file": "D:\\BD shopify\\apps\\web\\app\\%5Fsites\\[tenant]\\checkout\\actions.ts", "source_location": null, "source_url": null, "captured_at": null, "author": null, "contributor": null}, {"id": "lib_bkash", "label": "getEnabledBkash provider", "file_type": "code", "source_file": "D:\\BD shopify\\apps\\web\\app\\%5Fsites\\[tenant]\\checkout\\actions.ts", "source_location": null, "source_url": null, "captured_at": null, "author": null, "contributor": null}, {"id": "lib_sms_notify", "label": "sendOrderNotifications (Bengali SMS)", "file_type": "code", "source_file": "D:\\BD shopify\\apps\\web\\app\\%5Fsites\\[tenant]\\checkout\\actions.ts", "source_location": null, "source_url": null, "captured_at": null, "author": null, "contributor": null}, {"id": "lib_ratelimit", "label": "rateLimit / clientIpFrom", "file_type": "code", "source_file": "D:\\BD shopify\\apps\\web\\app\\%5Fsites\\[tenant]\\checkout\\actions.ts", "source_location": null, "source_url": null, "captured_at": null, "author": null, "contributor": null}], "edges": [{"source": "db_withTenant", "target": "02policies_app_current_tenant_id", "relation": "references", "confidence": "INFERRED", "confidence_score": 0.95, "source_file": "D:\\BD shopify\\apps\\web\\app\\%5Fsites\\[tenant]\\checkout\\actions.ts", "source_location": null, "weight": 0.95}, {"source": "checkout_actions", "target": "lib_place_order", "relation": "calls", "confidence": "EXTRACTED", "confidence_score": 1.0, "source_file": "D:\\BD shopify\\apps\\web\\app\\%5Fsites\\[tenant]\\checkout\\actions.ts", "source_location": null, "weight": 1.0}, {"source": "checkout_actions", "target": "lib_storefront_data", "relation": "calls", "confidence": "EXTRACTED", "confidence_score": 1.0, "source_file": "D:\\BD shopify\\apps\\web\\app\\%5Fsites\\[tenant]\\checkout\\actions.ts", "source_location": null, "weight": 1.0}, {"source": "checkout_actions", "target": "lib_bkash", "relation": "calls", "confidence": "EXTRACTED", "confidence_score": 1.0, "source_file": "D:\\BD shopify\\apps\\web\\app\\%5Fsites\\[tenant]\\checkout\\actions.ts", "source_location": null, "weight": 1.0}, {"source": "checkout_actions", "target": "lib_sms_notify", "relation": "calls", "confidence": "EXTRACTED", "confidence_score": 1.0, "source_file": "D:\\BD shopify\\apps\\web\\app\\%5Fsites\\[tenant]\\checkout\\actions.ts", "source_location": null, "weight": 1.0}, {"source": "checkout_actions", "target": "lib_ratelimit", "relation": "calls", "confidence": "EXTRACTED", "confidence_score": 1.0, "source_file": "D:\\BD shopify\\apps\\web\\app\\%5Fsites\\[tenant]\\checkout\\actions.ts", "source_location": null, "weight": 1.0}, {"source": "checkout_actions", "target": "db_withTenant", "relation": "calls", "confidence": "EXTRACTED", "confidence_score": 1.0, "source_file": "D:\\BD shopify\\apps\\web\\app\\%5Fsites\\[tenant]\\checkout\\actions.ts", "source_location": null, "weight": 1.0}, {"source": "checkout_actions", "target": "01schema_tenant_domain", "relation": "references", "confidence": "EXTRACTED", "confidence_score": 1.0, "source_file": "D:\\BD shopify\\apps\\web\\app\\%5Fsites\\[tenant]\\checkout\\actions.ts", "source_location": null, "weight": 1.0}, {"source": "lib_place_order", "target": "01schema_orders", "relation": "shares_data_with", "confidence": "INFERRED", "confidence_score": 0.85, "source_file": "D:\\BD shopify\\apps\\web\\app\\%5Fsites\\[tenant]\\checkout\\actions.ts", "source_location": null, "weight": 0.85}, {"source": "lib_place_order", "target": "01schema_product_variant", "relation": "references", "confidence": "INFERRED", "confidence_score": 0.85, "source_file": "D:\\BD shopify\\apps\\web\\app\\%5Fsites\\[tenant]\\checkout\\actions.ts", "source_location": null, "weight": 0.85}, {"source": "lib_place_order", "target": "01schema_payment", "relation": "references", "confidence": "INFERRED", "confidence_score": 0.85, "source_file": "D:\\BD shopify\\apps\\web\\app\\%5Fsites\\[tenant]\\checkout\\actions.ts", "source_location": null, "weight": 0.85}, {"source": "lib_bkash", "target": "01schema_payment_account", "relation": "references", "confidence": "INFERRED", "confidence_score": 0.75, "source_file": "D:\\BD shopify\\apps\\web\\app\\%5Fsites\\[tenant]\\checkout\\actions.ts", "source_location": null, "weight": 0.75}], "hyperedges": [{"id": "he_checkout_flow", "label": "Storefront checkout flow", "members": ["cart_usecart", "cart_island", "checkout_actions", "lib_place_order", "lib_bkash", "lib_sms_notify", "db_withTenant"], "relation": "conceptually_related_to", "confidence": "INFERRED", "confidence_score": 0.85, "source_file": "D:\\BD shopify\\apps\\web\\app\\%5Fsites\\[tenant]\\checkout\\actions.ts"}]}