{"nodes": [{"id": "OrderStatusActions_OrderStatusActions", "label": "OrderStatusActions", "file_type": "code", "source_file": "D:\\BD shopify\\apps\\web\\app\\(admin)\\admin\\orders\\[id]\\OrderStatusActions.tsx", "source_location": null, "source_url": null, "captured_at": null, "author": null, "contributor": null}], "edges": [{"source": "OrderStatusActions_OrderStatusActions", "target": "ext_updateOrderStatus", "relation": "calls", "confidence": "EXTRACTED", "confidence_score": 1.0, "source_file": "D:\\BD shopify\\apps\\web\\app\\(admin)\\admin\\orders\\[id]\\OrderStatusActions.tsx", "source_location": null, "weight": 1.0}], "hyperedges": []}