{"nodes": [{"id": "d_bd_shopify_apps_web_lib_couriers_sync_ts", "label": "sync.ts", "file_type": "code", "source_file": "D:\\BD shopify\\apps\\web\\lib\\couriers\\sync.ts", "source_location": "L1"}, {"id": "couriers_sync_activeshipment", "label": "ActiveShipment", "file_type": "code", "source_file": "D:\\BD shopify\\apps\\web\\lib\\couriers\\sync.ts", "source_location": "L19"}, {"id": "couriers_sync_synctenantshipments", "label": "syncTenantShipments()", "file_type": "code", "source_file": "D:\\BD shopify\\apps\\web\\lib\\couriers\\sync.ts", "source_location": "L29"}, {"id": "couriers_sync_reconcileone", "label": "reconcileOne()", "file_type": "code", "source_file": "D:\\BD shopify\\apps\\web\\lib\\couriers\\sync.ts", "source_location": "L65"}], "edges": [{"source": "d_bd_shopify_apps_web_lib_couriers_sync_ts", "target": "db", "relation": "imports_from", "context": "import", "confidence": "EXTRACTED", "source_file": "D:\\BD shopify\\apps\\web\\lib\\couriers\\sync.ts", "source_location": "L16", "weight": 1.0}, {"source": "d_bd_shopify_apps_web_lib_couriers_sync_ts", "target": "couriers", "relation": "imports_from", "context": "import", "confidence": "EXTRACTED", "source_file": "D:\\BD shopify\\apps\\web\\lib\\couriers\\sync.ts", "source_location": "L17", "weight": 1.0}, {"source": "d_bd_shopify_apps_web_lib_couriers_sync_ts", "target": "couriers_sync_activeshipment", "relation": "contains", "confidence": "EXTRACTED", "source_file": "D:\\BD shopify\\apps\\web\\lib\\couriers\\sync.ts", "source_location": "L19", "weight": 1.0}, {"source": "d_bd_shopify_apps_web_lib_couriers_sync_ts", "target": "couriers_sync_synctenantshipments", "relation": "contains", "confidence": "EXTRACTED", "source_file": "D:\\BD shopify\\apps\\web\\lib\\couriers\\sync.ts", "source_location": "L29", "weight": 1.0}, {"source": "d_bd_shopify_apps_web_lib_couriers_sync_ts", "target": "couriers_sync_reconcileone", "relation": "contains", "confidence": "EXTRACTED", "source_file": "D:\\BD shopify\\apps\\web\\lib\\couriers\\sync.ts", "source_location": "L65", "weight": 1.0}, {"source": "couriers_sync_synctenantshipments", "target": "couriers_sync_reconcileone", "relation": "calls", "context": "call", "confidence": "EXTRACTED", "source_file": "D:\\BD shopify\\apps\\web\\lib\\couriers\\sync.ts", "source_location": "L59", "weight": 1.0}], "raw_calls": [{"caller_nid": "couriers_sync_synctenantshipments", "callee": "withTenant", "is_member_call": false, "source_file": "D:\\BD shopify\\apps\\web\\lib\\couriers\\sync.ts", "source_location": "L34"}, {"caller_nid": "couriers_sync_synctenantshipments", "callee": "(tx) =>\n    tx<\n      {\n        id: string;\n        order_id: string;\n        consignment_id: string;\n        cod_amount: string;\n      }[]\n    >", "is_member_call": false, "source_file": "D:\\BD shopify\\apps\\web\\lib\\couriers\\sync.ts", "source_location": "L34"}, {"caller_nid": "couriers_sync_synctenantshipments", "callee": "Number", "is_member_call": false, "source_file": "D:\\BD shopify\\apps\\web\\lib\\couriers\\sync.ts", "source_location": "L57"}, {"caller_nid": "couriers_sync_reconcileone", "callee": "getStatus", "is_member_call": true, "source_file": "D:\\BD shopify\\apps\\web\\lib\\couriers\\sync.ts", "source_location": "L72"}, {"caller_nid": "couriers_sync_reconcileone", "callee": "withTenant", "is_member_call": false, "source_file": "D:\\BD shopify\\apps\\web\\lib\\couriers\\sync.ts", "source_location": "L75"}]}