{"nodes": [{"id": "d_bd_shopify_apps_web_app_admin_admin_settings_courier_actions_ts", "label": "actions.ts", "file_type": "code", "source_file": "D:\\BD shopify\\apps\\web\\app\\(admin)\\admin\\settings\\courier\\actions.ts", "source_location": "L1"}, {"id": "courier_actions_settingsresult", "label": "SettingsResult", "file_type": "code", "source_file": "D:\\BD shopify\\apps\\web\\app\\(admin)\\admin\\settings\\courier\\actions.ts", "source_location": "L20"}, {"id": "courier_actions_jsonb", "label": "Jsonb", "file_type": "code", "source_file": "D:\\BD shopify\\apps\\web\\app\\(admin)\\admin\\settings\\courier\\actions.ts", "source_location": "L26"}, {"id": "courier_actions_authtenant", "label": "authTenant()", "file_type": "code", "source_file": "D:\\BD shopify\\apps\\web\\app\\(admin)\\admin\\settings\\courier\\actions.ts", "source_location": "L28"}, {"id": "courier_actions_readsealed", "label": "readSealed()", "file_type": "code", "source_file": "D:\\BD shopify\\apps\\web\\app\\(admin)\\admin\\settings\\courier\\actions.ts", "source_location": "L38"}, {"id": "courier_actions_steadfastinput", "label": "SteadfastInput", "file_type": "code", "source_file": "D:\\BD shopify\\apps\\web\\app\\(admin)\\admin\\settings\\courier\\actions.ts", "source_location": "L47"}, {"id": "courier_actions_savesteadfast", "label": "saveSteadfast()", "file_type": "code", "source_file": "D:\\BD shopify\\apps\\web\\app\\(admin)\\admin\\settings\\courier\\actions.ts", "source_location": "L53"}], "edges": [{"source": "d_bd_shopify_apps_web_app_admin_admin_settings_courier_actions_ts", "target": "zod", "relation": "imports_from", "context": "import", "confidence": "EXTRACTED", "source_file": "D:\\BD shopify\\apps\\web\\app\\(admin)\\admin\\settings\\courier\\actions.ts", "source_location": "L13", "weight": 1.0}, {"source": "d_bd_shopify_apps_web_app_admin_admin_settings_courier_actions_ts", "target": "cache", "relation": "imports_from", "context": "import", "confidence": "EXTRACTED", "source_file": "D:\\BD shopify\\apps\\web\\app\\(admin)\\admin\\settings\\courier\\actions.ts", "source_location": "L14", "weight": 1.0}, {"source": "d_bd_shopify_apps_web_app_admin_admin_settings_courier_actions_ts", "target": "db", "relation": "imports_from", "context": "import", "confidence": "EXTRACTED", "source_file": "D:\\BD shopify\\apps\\web\\app\\(admin)\\admin\\settings\\courier\\actions.ts", "source_location": "L15", "weight": 1.0}, {"source": "d_bd_shopify_apps_web_app_admin_admin_settings_courier_actions_ts", "target": "db", "relation": "imports_from", "context": "import", "confidence": "EXTRACTED", "source_file": "D:\\BD shopify\\apps\\web\\app\\(admin)\\admin\\settings\\courier\\actions.ts", "source_location": "L16", "weight": 1.0}, {"source": "d_bd_shopify_apps_web_app_admin_admin_settings_courier_actions_ts", "target": "d_bd_shopify_apps_web_lib_auth_session_ts", "relation": "imports_from", "context": "import", "confidence": "EXTRACTED", "source_file": "D:\\BD shopify\\apps\\web\\app\\(admin)\\admin\\settings\\courier\\actions.ts", "source_location": "L17", "weight": 1.0}, {"source": "d_bd_shopify_apps_web_app_admin_admin_settings_courier_actions_ts", "target": "auth_session_getsession", "relation": "imports", "context": "import", "confidence": "EXTRACTED", "source_file": "D:\\BD shopify\\apps\\web\\app\\(admin)\\admin\\settings\\courier\\actions.ts", "source_location": "L17", "weight": 1.0}, {"source": "d_bd_shopify_apps_web_app_admin_admin_settings_courier_actions_ts", "target": "d_bd_shopify_apps_web_lib_admin_data_ts", "relation": "imports_from", "context": "import", "confidence": "EXTRACTED", "source_file": "D:\\BD shopify\\apps\\web\\app\\(admin)\\admin\\settings\\courier\\actions.ts", "source_location": "L18", "weight": 1.0}, {"source": "d_bd_shopify_apps_web_app_admin_admin_settings_courier_actions_ts", "target": "admin_data_getactivetenantid", "relation": "imports", "context": "import", "confidence": "EXTRACTED", "source_file": "D:\\BD shopify\\apps\\web\\app\\(admin)\\admin\\settings\\courier\\actions.ts", "source_location": "L18", "weight": 1.0}, {"source": "d_bd_shopify_apps_web_app_admin_admin_settings_courier_actions_ts", "target": "courier_actions_settingsresult", "relation": "contains", "confidence": "EXTRACTED", "source_file": "D:\\BD shopify\\apps\\web\\app\\(admin)\\admin\\settings\\courier\\actions.ts", "source_location": "L20", "weight": 1.0}, {"source": "d_bd_shopify_apps_web_app_admin_admin_settings_courier_actions_ts", "target": "courier_actions_jsonb", "relation": "contains", "confidence": "EXTRACTED", "source_file": "D:\\BD shopify\\apps\\web\\app\\(admin)\\admin\\settings\\courier\\actions.ts", "source_location": "L26", "weight": 1.0}, {"source": "d_bd_shopify_apps_web_app_admin_admin_settings_courier_actions_ts", "target": "courier_actions_authtenant", "relation": "contains", "confidence": "EXTRACTED", "source_file": "D:\\BD shopify\\apps\\web\\app\\(admin)\\admin\\settings\\courier\\actions.ts", "source_location": "L28", "weight": 1.0}, {"source": "d_bd_shopify_apps_web_app_admin_admin_settings_courier_actions_ts", "target": "courier_actions_readsealed", "relation": "contains", "confidence": "EXTRACTED", "source_file": "D:\\BD shopify\\apps\\web\\app\\(admin)\\admin\\settings\\courier\\actions.ts", "source_location": "L38", "weight": 1.0}, {"source": "d_bd_shopify_apps_web_app_admin_admin_settings_courier_actions_ts", "target": "courier_actions_steadfastinput", "relation": "contains", "confidence": "EXTRACTED", "source_file": "D:\\BD shopify\\apps\\web\\app\\(admin)\\admin\\settings\\courier\\actions.ts", "source_location": "L47", "weight": 1.0}, {"source": "d_bd_shopify_apps_web_app_admin_admin_settings_courier_actions_ts", "target": "courier_actions_savesteadfast", "relation": "contains", "confidence": "EXTRACTED", "source_file": "D:\\BD shopify\\apps\\web\\app\\(admin)\\admin\\settings\\courier\\actions.ts", "source_location": "L53", "weight": 1.0}, {"source": "courier_actions_savesteadfast", "target": "courier_actions_authtenant", "relation": "calls", "context": "call", "confidence": "EXTRACTED", "source_file": "D:\\BD shopify\\apps\\web\\app\\(admin)\\admin\\settings\\courier\\actions.ts", "source_location": "L57", "weight": 1.0}], "raw_calls": [{"caller_nid": "courier_actions_authtenant", "callee": "getSession", "is_member_call": false, "source_file": "D:\\BD shopify\\apps\\web\\app\\(admin)\\admin\\settings\\courier\\actions.ts", "source_location": "L31"}, {"caller_nid": "courier_actions_authtenant", "callee": "getActiveTenantId", "is_member_call": false, "source_file": "D:\\BD shopify\\apps\\web\\app\\(admin)\\admin\\settings\\courier\\actions.ts", "source_location": "L33"}, {"caller_nid": "courier_actions_readsealed", "callee": "isSealed", "is_member_call": false, "source_file": "D:\\BD shopify\\apps\\web\\app\\(admin)\\admin\\settings\\courier\\actions.ts", "source_location": "L39"}, {"caller_nid": "courier_actions_readsealed", "callee": "openCredentials", "is_member_call": false, "source_file": "D:\\BD shopify\\apps\\web\\app\\(admin)\\admin\\settings\\courier\\actions.ts", "source_location": "L41"}, {"caller_nid": "courier_actions_savesteadfast", "callee": "safeParse", "is_member_call": true, "source_file": "D:\\BD shopify\\apps\\web\\app\\(admin)\\admin\\settings\\courier\\actions.ts", "source_location": "L60"}, {"caller_nid": "courier_actions_savesteadfast", "callee": "get", "is_member_call": true, "source_file": "D:\\BD shopify\\apps\\web\\app\\(admin)\\admin\\settings\\courier\\actions.ts", "source_location": "L61"}, {"caller_nid": "courier_actions_savesteadfast", "callee": "get", "is_member_call": true, "source_file": "D:\\BD shopify\\apps\\web\\app\\(admin)\\admin\\settings\\courier\\actions.ts", "source_location": "L61"}, {"caller_nid": "courier_actions_savesteadfast", "callee": "get", "is_member_call": true, "source_file": "D:\\BD shopify\\apps\\web\\app\\(admin)\\admin\\settings\\courier\\actions.ts", "source_location": "L62"}, {"caller_nid": "courier_actions_savesteadfast", "callee": "get", "is_member_call": true, "source_file": "D:\\BD shopify\\apps\\web\\app\\(admin)\\admin\\settings\\courier\\actions.ts", "source_location": "L63"}, {"caller_nid": "courier_actions_savesteadfast", "callee": "withTenant", "is_member_call": false, "source_file": "D:\\BD shopify\\apps\\web\\app\\(admin)\\admin\\settings\\courier\\actions.ts", "source_location": "L69"}, {"caller_nid": "courier_actions_savesteadfast", "callee": "error", "is_member_call": true, "source_file": "D:\\BD shopify\\apps\\web\\app\\(admin)\\admin\\settings\\courier\\actions.ts", "source_location": "L98"}, {"caller_nid": "courier_actions_savesteadfast", "callee": "revalidateTag", "is_member_call": false, "source_file": "D:\\BD shopify\\apps\\web\\app\\(admin)\\admin\\settings\\courier\\actions.ts", "source_location": "L102"}]}